akeyless_proxy_api/__init__.py
akeyless_proxy_api/api_client.py
akeyless_proxy_api/configuration.py
akeyless_proxy_api/rest.py
akeyless_proxy_api/api/__init__.py
akeyless_proxy_api/api/default_api.py
akeyless_proxy_api/models/__init__.py
akeyless_proxy_api/models/error_reply_obj.py
akeyless_proxy_api/models/reply_obj.py
test/__init__.py
test/test_default_api.py
test/test_error_reply_obj.py
test/test_reply_obj.py
akeyless_proxy_api-0.1.1.dist-info/METADATA
akeyless_proxy_api-0.1.1.dist-info/WHEEL
akeyless_proxy_api-0.1.1.dist-info/top_level.txt
akeyless_proxy_api-0.1.1.dist-info/RECORD
